[1,["eaVJoq1odPdL00vPJSk+UU","d6sOZ7CdhGKKZwFLI8b1l1","daSpXCfedEIpyI7rc0EROa","4c1FNVOWRAz53pS3j1Dy2A","b8fQgVEKZEZJYY39XE69zP","d2MrKkdEFFhrbj9SEON92X","e8y4eK4VFLULXJdgMAW/x5","b5T8YBvDpGAJvHQn3VvUci","1apPuAZ8hOI5QRuznWqN/A","ab5FqtpPNLeZZ+IUzbnBiP","96x6CvSWJF1Z99MnucDku2","46dCqOsVtHqJXuNxO1nKwD","e082OXcERCr5Lzx9nlUfrT","4dLr8t+q1PKaWJFqdPGaYL","e4tPrgZTxPwqOWVN+ZlCfX"],["_textureSetter","bw","desc_bns","fsw","info1","info2","info3","info4","info5","info6","mw","smw","start_bns","tw_info","win_info"],["cc.SpriteFrame",["cc.SpriteAtlas",["_name","_spriteFrames"],2,11]],[[1,0,1,2]],[[[{"name":"info5","rect":[923,0,771,52],"offset":[-5,7],"originalSize":[781,84],"rotated":1,"capInsets":[0,0,0,0]}],[0],0,[0],[0],[0]],[[[0,"general.plist",[{},"bw",6,0,"desc_bns",6,1,"fsw",6,2,"info1",6,3,"info2",6,4,"info3",6,5,"info4",6,6,"info5",6,7,"info6",6,8,"mw",6,9,"smw",6,10,"start_bns",6,11,"tw_info",6,12,"win_info",6,13]]],0,0,[0,0,0,0,0,0,0,0,0,0,0,0,0,0],[1,2,3,4,5,6,7,8,9,10,11,12,13,14],[1,2,3,4,5,6,7,8,9,10,11,12,13,14]],[[{"name":"smw","rect":[0,364,534,365],"offset":[0,0],"originalSize":[536,367],"capInsets":[0,0,0,0]}],[0],0,[0],[0],[0]],[[{"name":"fsw","rect":[0,64,653,300],"offset":[-1,0],"originalSize":[655,304],"capInsets":[0,0,0,0]}],[0],0,[0],[0],[0]],[[{"name":"tw_info","rect":[632,938,102,82],"offset":[1,1],"originalSize":[112,84],"rotated":1,"capInsets":[0,0,0,0]}],[0],0,[0],[0],[0]],[[{"name":"mw","rect":[0,729,501,373],"offset":[0,0],"originalSize":[503,375],"capInsets":[0,0,0,0]}],[0],0,[0],[0],[0]],[[{"name":"info6","rect":[650,664,274,64],"offset":[0,-1],"originalSize":[280,84],"rotated":1,"capInsets":[0,0,0,0]}],[0],0,[0],[0],[0]],[[{"name":"info4","rect":[0,1102,637,64],"offset":[0,-2],"originalSize":[641,84],"capInsets":[0,0,0,0]}],[0],0,[0],[0],[0]],[[{"name":"info1","rect":[0,0,905,64],"offset":[-2,-1],"originalSize":[909,84],"capInsets":[0,0,0,0]}],[0],0,[0],[0],[0]],[[{"name":"info2","rect":[871,64,721,52],"offset":[-1,7],"originalSize":[723,84],"rotated":1,"capInsets":[0,0,0,0]}],[0],0,[0],[0],[0]],[[{"name":"bw","rect":[653,64,600,218],"offset":[0,0],"originalSize":[600,218],"rotated":1,"capInsets":[0,0,0,0]}],[0],0,[0],[0],[0]],[[{"name":"desc_bns","rect":[534,364,479,116],"offset":[0,0],"originalSize":[479,116],"rotated":1,"capInsets":[0,0,0,0]}],[0],0,[0],[0],[0]],[[{"name":"start_bns","rect":[501,843,237,69],"offset":[0,0],"originalSize":[237,69],"rotated":1,"capInsets":[0,0,0,0]}],[0],0,[0],[0],[0]],[[{"name":"win_info","rect":[570,843,153,62],"offset":[0,9],"originalSize":[161,84],"rotated":1,"capInsets":[0,0,0,0]}],[0],0,[0],[0],[0]],[[{"name":"info3","rect":[714,664,448,52],"offset":[0,6],"originalSize":[458,84],"rotated":1,"capInsets":[0,0,0,0]}],[0],0,[0],[0],[0]]]]