[1,["a75r/9hE9PL5gKFtHLpUic","4cVfCkDvpLCr81tUSxCQDF","d68E8tHXlAE4f7rFlNwY0a","b0MXOtRo5M8YteQ+xtElph","94A2tzsRZG84sNFesVCZ1v","3fU77cp5VO7I7atFRCLK76","85SDo90AdHBL8Dywc2+S0p","0eE/8U0KxEwqFCWVJkj7Lc","dbYsrmn+ZHoYCDhBW2/3bb","76dU0UKMlOpo8DDQedsVSw","54XIpPEE5Bk75neAifN6Y6"],["_textureSetter","info_1","info_2","info_3","info_4","info_5","info_6","info_7","info_8","info_fs","info_scatter"],["cc.SpriteFrame",["cc.SpriteAtlas",["_name","_spriteFrames"],2,11]],[[1,0,1,2]],[[[{"name":"info_7","rect":[1,291,441,56],"offset":[0,0],"originalSize":[441,56],"capInsets":[0,0,0,0]}],[0],0,[0],[0],[0]],[[[0,"infoboard_text.plist",[{},"info_1",6,0,"info_2",6,1,"info_3",6,2,"info_4",6,3,"info_5",6,4,"info_6",6,5,"info_7",6,6,"info_8",6,7,"info_fs",6,8,"info_scatter",6,9]]],0,0,[0,0,0,0,0,0,0,0,0,0],[1,2,3,4,5,6,7,8,9,10],[1,2,3,4,5,6,7,8,9,10]],[[{"name":"info_5","rect":[1,175,602,56],"offset":[0,0],"originalSize":[602,56],"capInsets":[0,0,0,0]}],[0],0,[0],[0],[0]],[[{"name":"info_1","rect":[1,1,602,56],"offset":[0,0],"originalSize":[602,56],"capInsets":[0,0,0,0]}],[0],0,[0],[0],[0]],[[{"name":"info_scatter","rect":[591,117,238,56],"offset":[0,0],"originalSize":[238,56],"capInsets":[0,0,0,0]}],[0],0,[0],[0],[0]],[[{"name":"info_fs","rect":[654,59,252,56],"offset":[0,0],"originalSize":[252,56],"capInsets":[0,0,0,0]}],[0],0,[0],[0],[0]],[[{"name":"info_6","rect":[1,233,616,56],"offset":[0,0],"originalSize":[616,56],"capInsets":[0,0,0,0]}],[0],0,[0],[0],[0]],[[{"name":"info_4","rect":[1,117,588,56],"offset":[0,0],"originalSize":[588,56],"capInsets":[0,0,0,0]}],[0],0,[0],[0],[0]],[[{"name":"info_3","rect":[1,59,651,56],"offset":[0,0],"originalSize":[651,56],"capInsets":[0,0,0,0]}],[0],0,[0],[0],[0]],[[{"name":"info_2","rect":[605,1,322,56],"offset":[0,0],"originalSize":[322,56],"capInsets":[0,0,0,0]}],[0],0,[0],[0],[0]],[[{"name":"info_8","rect":[444,291,546,56],"offset":[0,0],"originalSize":[546,56],"capInsets":[0,0,0,0]}],[0],0,[0],[0],[0]]]]