[1,["49enjjNyNBnKA8d94fyT5u","44TPXpTddI9qUzmbMcpWHF","60BPowQU5Jl7yf235XmqSo","218FStdSlP7a/y3iYPkT8m"],["_textureSetter","bonusgame","start","start_disabled"],["cc.SpriteFrame",["cc.SpriteAtlas",["_name","_spriteFrames"],2,11]],[[1,0,1,2]],[[[{"name":"start_disabled","rect":[1014,84,294,72],"offset":[0,0],"originalSize":[294,72],"capInsets":[0,0,0,0]}],[0],0,[0],[0],[0]],[[[0,"bonus_game_text_02.plist",[{},"bonusgame",6,0,"start",6,1,"start_disabled",6,2]]],0,0,[0,0,0],[1,2,3],[1,2,3]],[[{"name":"bonusgame","rect":[0,0,1014,198],"offset":[0,0],"originalSize":[1014,198],"capInsets":[0,0,0,0]}],[0],0,[0],[0],[0]],[[{"name":"start","rect":[1014,0,306,84],"offset":[0,0],"originalSize":[306,84],"capInsets":[0,0,0,0]}],[0],0,[0],[0],[0]]]]