[1,["c5WSj8ag9C8L5Tb4FmgF30","09pyei7Y9Jf5clK485eGEe","31UVgOwLdMcJQT9BerwT0d","09WW1dWx9DKql+UDNZRRxv","96mOoEa1xLE54Qe+tHzUI2","edjjb2x61FFoh4d6IwcFYy","d92BYPSANP+qez4EGjbN0Q"],["_textureSetter","fb_btn","fb_cancel","fb_cost","fb_decs","fb_start","fb_title"],["cc.SpriteFrame",["cc.SpriteAtlas",["_name","_spriteFrames"],2,11]],[[1,0,1,2]],[[[[0,"feature_buy.plist",[{},"fb_btn",6,0,"fb_cancel",6,1,"fb_cost",6,2,"fb_decs",6,3,"fb_start",6,4,"fb_title",6,5]]],0,0,[0,0,0,0,0,0],[1,2,3,4,5,6],[1,2,3,4,5,6]],[[{"name":"fb_cost","rect":[118,562,93,34],"offset":[0,0],"originalSize":[93,34],"rotated":1,"capInsets":[0,0,0,0]}],[0],0,[0],[0],[0]],[[{"name":"fb_btn","rect":[1,713,128,83],"offset":[0,0],"originalSize":[128,83],"capInsets":[0,0,0,0]}],[0],0,[0],[0],[0]],[[{"name":"fb_cancel","rect":[131,280,162,46],"offset":[0,0],"originalSize":[162,46],"rotated":1,"capInsets":[0,0,0,0]}],[0],0,[0],[0],[0]],[[{"name":"fb_decs","rect":[1,280,431,115],"offset":[0,0],"originalSize":[431,115],"rotated":1,"capInsets":[0,0,0,0]}],[0],0,[0],[0],[0]],[[{"name":"fb_title","rect":[1,1,277,183],"offset":[0,0],"originalSize":[277,183],"rotated":1,"capInsets":[0,0,0,0]}],[0],0,[0],[0],[0]],[[{"name":"fb_start","rect":[118,444,116,46],"offset":[0,0],"originalSize":[116,46],"rotated":1,"capInsets":[0,0,0,0]}],[0],0,[0],[0],[0]]]]