[1,["97ozyP4T5EIZ+W4I9uCi7E","1e7E0WpnlJcbXQlqCoeD8y","3dslqcXdJFqYBxcROt1EjO","d4a+QOH7tEk4hUYMf4uvoX"],["_textureSetter","big_win","mega_win","super_mega_win"],["cc.SpriteFrame",["cc.SpriteAtlas",["_name","_spriteFrames"],2,11]],[[1,0,1,2]],[[[{"name":"big_win","rect":[1125,1,449,206],"offset":[0,0],"originalSize":[449,206],"capInsets":[0,0,0,0]}],[0],0,[0],[0],[0]],[[{"name":"mega_win","rect":[1,1,409,216],"offset":[0,0],"originalSize":[409,216],"capInsets":[0,0,0,0]}],[0],0,[0],[0],[0]],[[[0,"bigwin_text.plist",[{},"big_win",6,0,"mega_win",6,1,"super_mega_win",6,2]]],0,0,[0,0,0],[1,2,3],[1,2,3]],[[{"name":"super_mega_win","rect":[412,1,711,213],"offset":[0,0],"originalSize":[711,213],"capInsets":[0,0,0,0]}],[0],0,[0],[0],[0]]]]