[1,["7bd/GkpSlJNb2olSHpeVDQ","66/mij4J1BQ7KmQUUjmetd"],["_textureSetter","spriteFrame"],["cc.SpriteFrame",["cc.BitmapFont",["_name","fontSize","_fntConfig"],0]],[[1,0,1,2,4]],[[[{"name":"bonus_info_m_one","rect":[3,3,185,241],"offset":[-1,1.5],"originalSize":[193,250],"capInsets":[0,0,0,0]}],[0],0,[0],[0],[0]],[[[0,"bonus_info_m_one",60,{"commonHeight":60,"fontSize":60,"atlasName":"bonus_info_m_one.png","fontDefDictionary":{"32":{"xOffset":0,"yOffset":42,"xAdvance":18,"rect":{"x":79,"y":211,"width":0,"height":0}},"44":{"xOffset":3,"yOffset":27,"xAdvance":15,"rect":{"x":42,"y":211,"width":17,"height":25}},"46":{"xOffset":3,"yOffset":27,"xAdvance":14,"rect":{"x":61,"y":211,"width":16,"height":16}},"48":{"xOffset":2,"yOffset":-7,"xAdvance":30,"rect":{"x":2,"y":57,"width":34,"height":50}},"49":{"xOffset":2,"yOffset":-8,"xAdvance":24,"rect":{"x":2,"y":109,"width":28,"height":50}},"50":{"xOffset":2,"yOffset":-7,"xAdvance":29,"rect":{"x":114,"y":109,"width":34,"height":49}},"51":{"xOffset":1,"yOffset":-7,"xAdvance":28,"rect":{"x":146,"y":57,"width":33,"height":50}},"52":{"xOffset":1,"yOffset":-7,"xAdvance":29,"rect":{"x":77,"y":109,"width":35,"height":49}},"53":{"xOffset":2,"yOffset":-8,"xAdvance":28,"rect":{"x":45,"y":2,"width":33,"height":51}},"54":{"xOffset":2,"yOffset":-7,"xAdvance":30,"rect":{"x":38,"y":57,"width":34,"height":50}},"55":{"xOffset":1,"yOffset":-6,"xAdvance":25,"rect":{"x":150,"y":109,"width":32,"height":49}},"56":{"xOffset":2,"yOffset":-7,"xAdvance":30,"rect":{"x":74,"y":57,"width":34,"height":50}},"57":{"xOffset":2,"yOffset":-7,"xAdvance":30,"rect":{"x":110,"y":57,"width":34,"height":50}},"67":{"xOffset":3,"yOffset":-7,"xAdvance":39,"rect":{"x":80,"y":2,"width":43,"height":50}},"84":{"xOffset":0,"yOffset":-7,"xAdvance":35,"rect":{"x":32,"y":109,"width":43,"height":49}},"99":{"xOffset":2,"yOffset":8,"xAdvance":24,"rect":{"x":159,"y":161,"width":30,"height":35}},"103":{"xOffset":1,"yOffset":8,"xAdvance":27,"rect":{"x":77,"y":161,"width":35,"height":45}},"104":{"xOffset":2,"yOffset":-8,"xAdvance":34,"rect":{"x":125,"y":2,"width":39,"height":50}},"110":{"xOffset":1,"yOffset":8,"xAdvance":33,"rect":{"x":2,"y":211,"width":38,"height":34}},"432":{"xOffset":1,"yOffset":2,"xAdvance":34,"rect":{"x":114,"y":161,"width":43,"height":41}},"7855":{"xOffset":2,"yOffset":-4,"xAdvance":27,"rect":{"x":42,"y":161,"width":33,"height":47}},"7893":{"xOffset":1,"yOffset":-5,"xAdvance":28,"rect":{"x":2,"y":161,"width":38,"height":48}},"7907":{"xOffset":1,"yOffset":1,"xAdvance":32,"rect":{"x":2,"y":2,"width":41,"height":53}}},"kerningDict":{"3014708":-2,"3014711":-4,"3014723":-4,"3014740":-4,"3407918":-1,"3407927":-2,"3604526":-4,"3604532":-3,"4390958":-1,"5505070":-2,"5505108":1,"5505123":-3,"6750254":-1}}]],0,0,[0],[1],[1]]]]