[1,["abIKGVyQ1Eloj0TBNf0Naq","a0sLeabMFNgZey58Qu+o+m","6f0ftvQIBGRKfTIwuY4GH1","01g9PTakVEDa8cHpe5DqQq","53renOiRlJH5Hh8bN/BVxf","facG8bJfBK6JbLaclpMy0G","f74KqfM2hCWIZofCzikHgd","a99dIvav9Ld4tOWZRlDHBp","19Lm8Z/OFEXYpjoY4366wa","d8bxvXLEVOmLel8iWMxh6I","72VcCIzvZP1o/UL95ydOlk","1a/bP98mtDy7kHLXrCtXKz","b0yY4l+y9PabzXXQJUWN8i"],["_textureSetter","info_bns1","info_bns2","info_main1","info_main2","info_main3","info_main4","info_main5","info_main6","info_scatter","info_tw","info_ways","info_win"],["cc.SpriteFrame",["cc.SpriteAtlas",["_name","_spriteFrames"],2,11]],[[1,0,1,2]],[[[{"name":"info_main1","rect":[62,0,608,66],"offset":[2,0],"originalSize":[616,70],"rotated":1,"capInsets":[0,0,0,0]}],[0],0,[0],[0],[0]],[[{"name":"info_main6","rect":[116,612,447,46],"offset":[-1,-4],"originalSize":[455,70],"rotated":1,"capInsets":[0,0,0,0]}],[0],0,[0],[0],[0]],[[{"name":"info_ways","rect":[116,1059,187,30],"offset":[-1,0],"originalSize":[189,70],"rotated":1,"capInsets":[0,0,0,0]}],[0],0,[0],[0],[0]],[[[0,"info_messages.plist",[{},"info_bns1",6,0,"info_bns2",6,1,"info_main1",6,2,"info_main2",6,3,"info_main3",6,4,"info_main4",6,5,"info_main5",6,6,"info_main6",6,7,"info_scatter",6,8,"info_tw",6,9,"info_ways",6,10,"info_win",6,11]]],0,0,[0,0,0,0,0,0,0,0,0,0,0,0],[1,2,3,4,5,6,7,8,9,10,11,12],[1,2,3,4,5,6,7,8,9,10,11,12]],[[{"name":"info_main2","rect":[188,484,474,46],"offset":[0,-4],"originalSize":[490,70],"rotated":1,"capInsets":[0,0,0,0]}],[0],0,[0],[0],[0]],[[{"name":"info_bns2","rect":[0,0,619,62],"offset":[-1,0],"originalSize":[623,70],"rotated":1,"capInsets":[0,0,0,0]}],[0],0,[0],[0],[0]],[[{"name":"info_tw","rect":[98,1246,105,38],"offset":[0,-2],"originalSize":[105,70],"capInsets":[0,0,0,0]}],[0],0,[0],[0],[0]],[[{"name":"info_bns1","rect":[0,619,619,58],"offset":[-1,0],"originalSize":[623,70],"rotated":1,"capInsets":[0,0,0,0]}],[0],0,[0],[0],[0]],[[{"name":"info_main5","rect":[188,0,484,46],"offset":[-1,-4],"originalSize":[490,70],"rotated":1,"capInsets":[0,0,0,0]}],[0],0,[0],[0],[0]],[[{"name":"info_win","rect":[0,1238,98,50],"offset":[0,-2],"originalSize":[98,70],"capInsets":[0,0,0,0]}],[0],0,[0],[0],[0]],[[{"name":"info_scatter","rect":[162,958,246,66],"offset":[0,0],"originalSize":[252,70],"rotated":1,"capInsets":[0,0,0,0]}],[0],0,[0],[0],[0]],[[{"name":"info_main4","rect":[128,0,612,60],"offset":[-1,0],"originalSize":[616,70],"rotated":1,"capInsets":[0,0,0,0]}],[0],0,[0],[0],[0]],[[{"name":"info_main3","rect":[58,619,614,58],"offset":[-1,0],"originalSize":[616,70],"rotated":1,"capInsets":[0,0,0,0]}],[0],0,[0],[0],[0]]]]