{"CommonRulesShared":{"InGameCurrency":"游戏金额以 %{configuredValue} 为单位。","CashWallet":"“现金钱包”用来显示下注者可用的现金余额。","WinShownInCash":"所有赢奖以现金显示。","BackAction":"点击离开游戏， 并返回上一层。","GameLobbyAction":"点击离开游戏，并进入PG游戏大厅。","GameHistoryDescription":"显示游戏历史记录详情。下滑到页面底部可加载更多记录。","GameHistoryActionWithIcon":"点击<img src='game-rules-sprite game-rules-ic_nav_calender'/>选择日期范围，显示相应的历史记录。","ReturnToPlayerDescription":"该游戏的返还率（RTP）为 %{rtpValue}。该RTP表示游戏在长期统计中，作为奖金支付的总投注金额的百分比。RTP值通过多轮游戏模拟中的总奖金与总投注金额的比值计算得出。","AdditionInfoMalfunctionDescription":"如遇任何机械故障，所有游戏及奖金（派彩）一律作废。","AdditionInfoInactiveGameSessions":"如果游戏闲置时长超过%{dayCount}天，游戏将自动恢复至初始状态。收集类的游戏进度、未完成的免费游戏、未完成的特色游戏以及等状态将不再保留。","AdditionInfoInactiveGameSessionsHour":"如果游戏闲置时长超过%{hourCount}小时，游戏将自动恢复至初始状态。收集类的游戏进度、未完成的免费游戏、未完成的特色游戏以及等状态将不再保留。","AdditionInfoDisputeHistoryDescription":"任何因游戏结果所产生的争议，均以游戏历史页面中所显示的记录为最终依据。","AdditionInfoInactiveGameSessionsAlternate":"任何因网络中断、技术问题或玩家主动退出而导致中断的游戏回合，将保持有效，不会被作废。玩家下次游戏时，将从中断点继续未完成的游戏回合。"},"SlotRulesShared":{"BetSize":"投注大小可以在“投注大小”选项中设定。","BetLevel":"投注倍数可以在“投注倍数”选项中设定。","BetAmount":"投注总额可以在“投注总额”选项中设定。","AutoSpinPlays":"“自动旋转”可以根据玩家所选择的回合数量自动进行游戏。","PayoutAccordingToPaytable":"中奖组合和奖金派发是根据“赔付表”进行的。","MainGameTitle":"主游戏","SpinTitle":"旋转按钮","FastStopAction":"旋转过程中单击按钮或游戏区可以马上停止当前旋转。","PCVersionTitle":"仅适用于桌面版","HoldSpaceBarAction":"按住空格键，将持续进行旋转，直到松开空格键。","SpaceBarStopReelAction":"当卷轴旋转时，按下空格键即可跳过旋转动画，直接查看结果（视网络连接稳定性而定）。","SpaceBarOneButtonAction":"当屏幕上仅显示一个可用按钮时，按下空格键即可激活它。","StopTitle":"停止按钮","StopAutoSpinAction":"单击按钮停止旋转。在自动游戏模式，剩余旋转次数会显示在按钮中。","SpinOptionTitle":"旋转设置","SpinSpeedSelection":"旋转速度可被设置为常速或极速（主游戏卷轴的旋转时间将减少）。","AutoSpinPlayDescription":"自动旋转可以根据选的次数进行自动游戏。","SelectAutoSpinRound":"次数： 点击所选次数进行自动游戏。","StopAutoSpinIfWinExceed":"停止旋转单次赢得超过金额（玩家指定数值）：当单次旋转赢得超过指定金额时，自动旋转将自动停止。","StopAutoSpinIfBalanceIncrease":"停止旋转余额增加超过金额（玩家指定数值）：当余额的增幅超过指定金额时（与自动旋转开始前相比），自动旋转将自动停止。","StopAutoSpinIfBalanceDecrease":"停止旋转余额减少超过金额（玩家指定数值）：当余额的减幅超过指定金额时（与自动旋转开始前相比），自动旋转将自动停止。","BetOptionsTitle":"投注设置","BetSizeAction":"投注大小：拖动以选择投注大小。","BetLevelAction":"投注倍数：拖动以选择投注倍数。","BetAmountAction":"投注总额：拖动以选择投注金额。","MaxBetAction":"最大投注：点击按钮可以把投注大小、投注倍数的数值调到最大。","MoreTitle":"更多","MoreAction":"点击进入“声音设置”、“赔付表”、“游戏规则”和“历史记录”。","MoreSettingTitle":"更多设置","SoundTitle":"声音","SoundAction":"点击打开或关闭游戏声音。","PaytableTitle":"赔付表","PaytableAction":"显示中奖组合以及赔付表。","GameRuleTitle":"规则","GameRuleAction":"显示游戏规则和按键功能。","GameHistoryTitle":"历史","CloseTitle":"关闭","CloseAction":"点击回到主游戏。","ReturnToPlayerTitle":"返还率","AdditionInfoTitle":"附加信息","TurboSpinTitle":"极速旋转","TurboSpinAction":"点击打开或关闭极速旋转。","BackTitle":"返回","PayoutProbabilities":"%{value}次旋转中出现1次"},"SlotRulesBetLineRelated":{"WinDetailBreakdown":"一条中奖线所得的奖励等同于显示在“赔付表”上的符号赔付值乘以投注大小和投注倍数。","HighestWinIsPaid":"只支付每条中奖线中赢取最高的奖金。","WinFromLeftmost":"中奖线奖金按照从最左至右卷轴的顺序派发。","SimultanuousWin":"不同中奖线上的奖金会被叠加。","SpinAction":"单击后可在当前中奖线、投注大小和投注倍数下开始游戏。","PressSpaceAction":"按下空格键，使用当前的投注线数、投注大小和投注倍数进行旋转。"},"SlotRulesBetWaysRelated":{"WinDetailBreakdown":"一条中奖路所得的奖励等同于显示在“赔付表”上的符号赔付值乘以投注大小和投注倍数。","BetWaysWin":"中奖路奖金按照从最左至右卷轴的顺序派发。","TotalOfBetWaysWin":"中奖路的奖金计算方式是按照从卷轴的最左边到最右边，每个赢奖符号相邻的数目乘以该符号的中奖路数目。","WinningSymbolPayout":"赢奖符号的赔付是由该符号的赔付值乘以中奖路的数目所得。","SimultaneousWin":"不同中奖路上的奖金会被叠加。"},"SlotRulesBaseBetRelated":{"SpinAction":"单击后可在当前基础投注、投注大小和投注倍数下开始游戏。","PressSpaceAction":"按下空格键，使用当前的基础投注、投注大小和投注倍数进行旋转。"}}