[1,["28ApzsXAFJAIEJ0lVwqQPx","87ILA1vyxPaIvhkR8EGDhr","573tpgCg9Mr61XrI3goN/b"],["_textureSetter","lfs","rfs"],["cc.SpriteFrame",["cc.SpriteAtlas",["_name","_spriteFrames"],2,11]],[[1,0,1,2]],[[[[0,"free_spin_text.plist",[{},"lfs",6,0,"rfs",6,1]]],0,0,[0,0],[1,2],[1,2]],[[{"name":"rfs","rect":[466,1,430,165],"offset":[0,0],"originalSize":[430,165],"capInsets":[0,0,0,0]}],[0],0,[0],[0],[0]],[[{"name":"lfs","rect":[1,1,463,173],"offset":[0,0],"originalSize":[463,173],"capInsets":[0,0,0,0]}],[0],0,[0],[0],[0]]]]