[1,["92O7MIQJlBu4HMO1AgVyh+"],["_textureSetter"],["cc.SpriteFrame"],0,[[[{"name":"info_3","rect":[1480,86,33,44],"offset":[0,0],"originalSize":[33,44],"capInsets":[0,0,0,0]}],[0],0,[0],[0],[0]],[[{"name":"info_9","rect":[1515,98,32,44],"offset":[0,0],"originalSize":[32,44],"rotated":1,"capInsets":[0,0,0,0]}],[0],0,[0],[0],[0]],[[{"name":"info_1","rect":[1517,132,26,44],"offset":[0,0],"originalSize":[26,44],"capInsets":[0,0,0,0]}],[0],0,[0],[0],[0]],[[{"name":"info_0","rect":[1445,132,36,44],"offset":[0,0],"originalSize":[36,44],"capInsets":[0,0,0,0]}],[0],0,[0],[0],[0]],[[{"name":"info_4","rect":[1525,224,31,43],"offset":[0,0],"originalSize":[31,43],"rotated":1,"capInsets":[0,0,0,0]}],[0],0,[0],[0],[0]],[[{"name":"info_8","rect":[1480,178,34,44],"offset":[0,0],"originalSize":[34,44],"capInsets":[0,0,0,0]}],[0],0,[0],[0],[0]],[[{"name":"info_2","rect":[1480,224,31,43],"offset":[0,0],"originalSize":[31,43],"rotated":1,"capInsets":[0,0,0,0]}],[0],0,[0],[0],[0]],[[{"name":"info_5","rect":[1545,132,31,43],"offset":[0,0],"originalSize":[31,43],"capInsets":[0,0,0,0]}],[0],0,[0],[0],[0]],[[{"name":"info_6","rect":[1483,132,32,44],"offset":[0,0],"originalSize":[32,44],"capInsets":[0,0,0,0]}],[0],0,[0],[0],[0]],[[{"name":"info_7","rect":[1516,178,29,44],"offset":[0,0],"originalSize":[29,44],"capInsets":[0,0,0,0]}],[0],0,[0],[0],[0]]]]