[1,["daiCpYOVFLfYSwzjHpq/yL","bapB/lkYdCrIK4rtuioUjS","7eqXmhBlRHxbIGRJgNhKBi","1eDArttS9DdLJHycd+qpVy","ecy+bkTLJHPYtb46TR4mD7","ebXjfOL0hOuoThgqthJdgX","ccpMdAkHlAAr/bITgrJwko","97r9+Rdz1Ew5Xz61j3dAY0","9eKDG+xNtARKNT8+02g3Ht","03xBBnYCVHUq21wUzYTRIR","96Pp7VsIFOwLRui+wsK+l/","a70azU5cRNwq+O0OOxpM6Z","dfMSxAMRFL0IXdNpW3Xsh4","c2183W1gVDRJZujVRdjtZE","0dXJ6UX4lM66wU4lrlYmSr","81ZtZB6XpFC761w68WlFXF","bb+ynzgnxAnrZUszsSV+me","8dA9geqO1MqoDYylVgGyhR","ddCPILYllBIbDY0I9trP4V","92mMuYHyJLFJ5eTEmJkjDg","a93emes3VKPbNtQka/bgTl"],["_textureSetter","h2_punchbag_frame_a","h2_punchbag_frame_a_blur","h2_punchbag_frame_b","h2_punchbag_frame_b_blur","h2_punchbag_frame_c","h2_punchbag_frame_c_blur","h2_punchbag_frame_d","h2_punchbag_frame_d_blur","h2_punchbag_frame_e","h2_punchbag_frame_e_blur","h2_punchingbag_a","h2_punchingbag_a_blur","h2_punchingbag_b","h2_punchingbag_b_blur","h2_punchingbag_c","h2_punchingbag_c_blur","h2_punchingbag_d","h2_punchingbag_d_blur","h2_punchingbag_e","h2_punchingbag_e_blur"],["cc.SpriteFrame",["cc.SpriteAtlas",["_name","_spriteFrames"],2,11]],[[1,0,1,2]],[[[{"name":"h2_punchbag_frame_e","rect":[1,1,350,1000],"offset":[0,0],"originalSize":[350,1000],"capInsets":[0,0,0,0]}],[0],0,[0],[0],[0]],[[{"name":"h2_punchingbag_b_blur","rect":[1411,1534,175,175],"offset":[0,0],"originalSize":[175,175],"capInsets":[0,0,0,0]}],[0],0,[0],[0],[0]],[[{"name":"h2_punchbag_frame_b","rect":[1057,353,350,350],"offset":[0,0],"originalSize":[350,350],"capInsets":[0,0,0,0]}],[0],0,[0],[0],[0]],[[[0,"symbols_high_payout_punching_bag.plist",[{},"h2_punchbag_frame_a",6,0,"h2_punchbag_frame_a_blur",6,1,"h2_punchbag_frame_b",6,2,"h2_punchbag_frame_b_blur",6,3,"h2_punchbag_frame_c",6,4,"h2_punchbag_frame_c_blur",6,5,"h2_punchbag_frame_d",6,6,"h2_punchbag_frame_d_blur",6,7,"h2_punchbag_frame_e",6,8,"h2_punchbag_frame_e_blur",6,9,"h2_punchingbag_a",6,10,"h2_punchingbag_a_blur",6,11,"h2_punchingbag_b",6,12,"h2_punchingbag_b_blur",6,13,"h2_punchingbag_c",6,14,"h2_punchingbag_c_blur",6,15,"h2_punchingbag_d",6,16,"h2_punchingbag_d_blur",6,17,"h2_punchingbag_e",6,18,"h2_punchingbag_e_blur",6,19]]],0,0,[0,0,0,0,0,0,0,0,0,0,0,0,0,0,0,0,0,0,0,0],[1,2,3,4,5,6,7,8,9,10,11,12,13,14,15,16,17,18,19,20],[1,2,3,4,5,6,7,8,9,10,11,12,13,14,15,16,17,18,19,20]],[[{"name":"h2_punchbag_frame_a_blur","rect":[1057,1586,175,175],"offset":[0,0],"originalSize":[175,175],"capInsets":[0,0,0,0]}],[0],0,[0],[0],[0]],[[{"name":"h2_punchingbag_c","rect":[353,1003,350,700],"offset":[0,0],"originalSize":[350,700],"capInsets":[0,0,0,0]}],[0],0,[0],[0],[0]],[[{"name":"h2_punchingbag_d","rect":[705,703,350,700],"offset":[0,0],"originalSize":[350,700],"capInsets":[0,0,0,0]}],[0],0,[0],[0],[0]],[[{"name":"h2_punchingbag_e","rect":[353,1,350,1000],"offset":[0,0],"originalSize":[350,1000],"capInsets":[0,0,0,0]}],[0],0,[0],[0],[0]],[[{"name":"h2_punchbag_frame_e_blur","rect":[1409,1,175,500],"offset":[0,0],"originalSize":[175,500],"capInsets":[0,0,0,0]}],[0],0,[0],[0],[0]],[[{"name":"h2_punchbag_frame_d","rect":[705,1,350,700],"offset":[0,0],"originalSize":[350,700],"capInsets":[0,0,0,0]}],[0],0,[0],[0],[0]],[[{"name":"h2_punchbag_frame_d_blur","rect":[1409,1005,175,350],"offset":[0,0],"originalSize":[175,350],"capInsets":[0,0,0,0]}],[0],0,[0],[0],[0]],[[{"name":"h2_punchingbag_a","rect":[1057,705,350,350],"offset":[0,0],"originalSize":[350,350],"capInsets":[0,0,0,0]}],[0],0,[0],[0],[0]],[[{"name":"h2_punchingbag_e_blur","rect":[1409,503,175,500],"offset":[0,0],"originalSize":[175,500],"capInsets":[0,0,0,0]}],[0],0,[0],[0],[0]],[[{"name":"h2_punchbag_frame_a","rect":[1057,1,350,350],"offset":[0,0],"originalSize":[350,350],"capInsets":[0,0,0,0]}],[0],0,[0],[0],[0]],[[{"name":"h2_punchingbag_c_blur","rect":[1057,1409,175,350],"offset":[0,0],"originalSize":[175,350],"rotated":1,"capInsets":[0,0,0,0]}],[0],0,[0],[0],[0]],[[{"name":"h2_punchingbag_b","rect":[1057,1057,350,350],"offset":[0,0],"originalSize":[350,350],"capInsets":[0,0,0,0]}],[0],0,[0],[0],[0]],[[{"name":"h2_punchbag_frame_c_blur","rect":[705,1405,175,350],"offset":[0,0],"originalSize":[175,350],"rotated":1,"capInsets":[0,0,0,0]}],[0],0,[0],[0],[0]],[[{"name":"h2_punchingbag_d_blur","rect":[705,1582,175,350],"offset":[0,0],"originalSize":[175,350],"rotated":1,"capInsets":[0,0,0,0]}],[0],0,[0],[0],[0]],[[{"name":"h2_punchingbag_a_blur","rect":[1409,1357,175,175],"offset":[0,0],"originalSize":[175,175],"capInsets":[0,0,0,0]}],[0],0,[0],[0],[0]],[[{"name":"h2_punchbag_frame_c","rect":[1,1003,350,700],"offset":[0,0],"originalSize":[350,700],"capInsets":[0,0,0,0]}],[0],0,[0],[0],[0]],[[{"name":"h2_punchbag_frame_b_blur","rect":[1234,1586,175,175],"offset":[0,0],"originalSize":[175,175],"capInsets":[0,0,0,0]}],[0],0,[0],[0],[0]]]]